auth_app/__init__.py
auth_app/admin.py
auth_app/admin_decorator.py
auth_app/apps.py
auth_app/backends.py
auth_app/decorators.py
auth_app/models.py
auth_app/orator_config.py
auth_app/tests.py
auth_app/urls.py
auth_app/views.py
auth_app/management/__init__.py
auth_app/management/commands/__init__.py
auth_app/management/commands/ai.py
auth_app/management/commands/seed.py
iceburgcrm/__init__.py
iceburgcrm/apps.py
iceburgcrm/asgi.py
iceburgcrm/context_processors.py
iceburgcrm/middleware.py
iceburgcrm/models.py
iceburgcrm/settings.py
iceburgcrm/urls.py
iceburgcrm/views.py
iceburgcrm/wsgi.py
iceburgcrm/models/__init__.py
iceburgcrm/models/admin.py
iceburgcrm/models/ai_assist.py
iceburgcrm/models/ai_create.py
iceburgcrm/models/base.py
iceburgcrm/models/connector.py
iceburgcrm/models/crm_builder.py
iceburgcrm/models/datalet.py
iceburgcrm/models/datalet_type.py
iceburgcrm/models/endpoint.py
iceburgcrm/models/field.py
iceburgcrm/models/field_seeder.py
iceburgcrm/models/field_type.py
iceburgcrm/models/log.py
iceburgcrm/models/module.py
iceburgcrm/models/module_convertable.py
iceburgcrm/models/module_group.py
iceburgcrm/models/module_subpanel.py
iceburgcrm/models/permission.py
iceburgcrm/models/relationship.py
iceburgcrm/models/relationship_module.py
iceburgcrm/models/role.py
iceburgcrm/models/schedule.py
iceburgcrm/models/search.py
iceburgcrm/models/settings.py
iceburgcrm/models/subpanel_field.py
iceburgcrm/models/theme.py
iceburgcrm/models/user.py
iceburgcrm/models/validation.py
iceburgcrm/models/work_flow_data.py
iceburgcrm/views/__init__.py
iceburgcrm/views/admin.py
iceburgcrm/views/admin_data.py
iceburgcrm/views/data.py
iceburgcrm/views/web.py
iceburgcrm-5.5.5.dist-info/LICENSE
iceburgcrm-5.5.5.dist-info/METADATA
iceburgcrm-5.5.5.dist-info/WHEEL
iceburgcrm-5.5.5.dist-info/top_level.txt
iceburgcrm-5.5.5.dist-info/RECORD
