Metadata-Version: 2.1
Name: iceburgcrm
Version: 5.5.5
Summary: Iceburg CRM is a metadata driven CRM in django python that allows you to quickly prototype any CRM. The default CRM is based on a typical business CRM but the flexibility of dynamic modules, fields, subpanels allows prototyping of any number of different tyes of CRMs.
Home-page: https://www.iceburg.ca
Author: Robert Devenyi
Author-email: rob@iceburg.ca
License: UNKNOWN
Project-URL: Homepage, https://github.com/iceburgcrm/iceburgcrmpython
Project-URL: Demo, https://demo.iceburg.ca
Platform: UNKNOWN
Classifier: Framework :: Django
Requires-Python: >=3.8
License-File: LICENSE
